{
  "elements" : [ {
    "allowOverride" : false,
    "combinationType" : "FUNCTION",
    "displayOptions" : 16,
    "elementGroups" : [ ],
    "elementLabel" : "ProductCost",
    "elementName" : "ProductCost",
    "elementTimeout" : 0,
    "excludeFromExport" : false,
    "hideOnNull" : false,
    "hideWarnings" : false,
    "protectedExpression" : false,
    "summarize" : false
  }, {
    "allowOverride" : false,
    "combinationType" : "FUNCTION",
    "displayOptions" : 16,
    "elementGroups" : [ ],
    "elementName" : "CountryCode",
    "elementTimeout" : 0,
    "excludeFromExport" : false,
    "hideOnNull" : false,
    "hideWarnings" : false,
    "overridden" : false,
    "protectedExpression" : false,
    "summarize" : false
  }, {
    "allowOverride" : false,
    "combinationType" : "FUNCTION",
    "displayOptions" : 0,
    "elementGroups" : [ ],
    "elementName" : "AbortOnInputGeneration",
    "elementTimeout" : 0,
    "excludeFromExport" : false,
    "hideOnNull" : false,
    "hideWarnings" : false,
    "overridden" : false,
    "protectedExpression" : false,
    "summarize" : false
  }, {
    "allowOverride" : false,
    "combinationType" : "FUNCTION",
    "displayOptions" : 16,
    "elementGroups" : [ ],
    "elementLabel" : "Base Price",
    "elementName" : "BasePrice",
    "elementTimeout" : 0,
    "excludeFromExport" : false,
    "formatType" : "MONEY_EUR",
    "hideOnNull" : false,
    "hideWarnings" : false,
    "labelTranslations" : { },
    "overridden" : false,
    "protectedExpression" : false,
    "summarize" : false
  }, {
    "allowOverride" : false,
    "combinationType" : "FUNCTION",
    "displayOptions" : 16,
    "elementGroups" : [ ],
    "elementLabel" : "Margin Adj %",
    "elementName" : "MarginAdjPct",
    "elementTimeout" : 0,
    "excludeFromExport" : false,
    "formatType" : "PERCENT",
    "hideOnNull" : false,
    "hideWarnings" : false,
    "overridden" : false,
    "protectedExpression" : false,
    "summarize" : false
  }, {
    "allowOverride" : false,
    "combinationType" : "FUNCTION",
    "displayOptions" : 16,
    "elementGroups" : [ ],
    "elementLabel" : "Margin Adj €",
    "elementName" : "MarginAdjAbs",
    "elementTimeout" : 0,
    "excludeFromExport" : false,
    "formatType" : "MONEY_EUR",
    "hideOnNull" : false,
    "hideWarnings" : false,
    "overridden" : false,
    "protectedExpression" : false,
    "summarize" : false
  }, {
    "allowOverride" : false,
    "combinationType" : "FUNCTION",
    "displayOptions" : 16,
    "elementGroups" : [ ],
    "elementLabel" : "Attribute Adj %",
    "elementName" : "AttributeAdjPct",
    "elementTimeout" : 0,
    "excludeFromExport" : false,
    "formatType" : "PERCENT",
    "hideOnNull" : false,
    "hideWarnings" : false,
    "overridden" : false,
    "protectedExpression" : false,
    "summarize" : false
  }, {
    "allowOverride" : false,
    "combinationType" : "FUNCTION",
    "displayOptions" : 16,
    "elementGroups" : [ ],
    "elementLabel" : "Attribute Adj €",
    "elementName" : "AttributeAdjAbs",
    "elementTimeout" : 0,
    "excludeFromExport" : false,
    "formatType" : "MONEY_EUR",
    "hideOnNull" : false,
    "hideWarnings" : false,
    "overridden" : false,
    "protectedExpression" : false,
    "summarize" : false
  }, {
    "allowOverride" : false,
    "combinationType" : "FUNCTION",
    "displayOptions" : 16,
    "elementGroups" : [ ],
    "elementLabel" : "Country Adj %",
    "elementName" : "CountryAdjPct",
    "elementTimeout" : 0,
    "excludeFromExport" : false,
    "formatType" : "PERCENT",
    "hideOnNull" : false,
    "hideWarnings" : false,
    "overridden" : false,
    "protectedExpression" : false,
    "summarize" : false
  }, {
    "allowOverride" : false,
    "combinationType" : "FUNCTION",
    "displayOptions" : 16,
    "elementGroups" : [ ],
    "elementLabel" : "Country Adj €",
    "elementName" : "CountryAdjAbs",
    "elementTimeout" : 0,
    "excludeFromExport" : false,
    "formatType" : "MONEY_EUR",
    "hideOnNull" : false,
    "hideWarnings" : false,
    "overridden" : false,
    "protectedExpression" : false,
    "summarize" : false
  }, {
    "allowOverride" : false,
    "combinationType" : "FUNCTION",
    "displayOptions" : 16,
    "elementGroups" : [ ],
    "elementLabel" : "List Price",
    "elementName" : "ListPrice",
    "elementTimeout" : 0,
    "excludeFromExport" : false,
    "formatType" : "MONEY_EUR",
    "hideOnNull" : false,
    "hideWarnings" : false,
    "overridden" : false,
    "protectedExpression" : false,
    "summarize" : false
  }, {
    "allowOverride" : false,
    "combinationType" : "FUNCTION",
    "displayOptions" : 16,
    "elementGroups" : [ ],
    "elementLabel" : "Cost",
    "elementName" : "Cost",
    "elementTimeout" : 0,
    "excludeFromExport" : false,
    "formatType" : "MONEY_EUR",
    "hideOnNull" : false,
    "hideWarnings" : false,
    "overridden" : false,
    "protectedExpression" : false,
    "summarize" : false
  }, {
    "allowOverride" : false,
    "combinationType" : "FUNCTION",
    "displayOptions" : 16,
    "elementGroups" : [ ],
    "elementLabel" : "Gross Margin %",
    "elementName" : "GrossMarginPct",
    "elementTimeout" : 0,
    "excludeFromExport" : false,
    "formatType" : "PERCENT",
    "hideOnNull" : false,
    "hideWarnings" : false,
    "overridden" : false,
    "protectedExpression" : false,
    "summarize" : false
  } ],
  "inputDescriptors" : [ ],
  "status" : "ACTIVE",
  "uniqueName" : "PG_Batching_Line",
  "validAfter" : "2020-01-01"
}